{
  "slug": "celecoxib",
  "nome": "Celecoxib",
  "atc": "M01AH01",
  "categoria_atc": "Sistema muscolo-scheletrico",
  "n_farmaci": 3,
  "prezzo_min": 9.52,
  "prezzo_medio": 16.75,
  "ha_rimborsato": true,
  "aggiornato": "2026-05-16",
  "farmaci": [
    {
      "nome": "Celecoxib EG 200mg 30cps",
      "ditta": "EG",
      "prezzo": 9.52,
      "fascia": "A",
      "rimborso": true
    },
    {
      "nome": "Celebrex 200mg 30cps",
      "ditta": "Pfizer",
      "prezzo": 20.52,
      "fascia": "A",
      "rimborso": true
    },
    {
      "nome": "Solexa 200mg 30cps",
      "ditta": "Pfizer",
      "prezzo": 20.22,
      "fascia": "A",
      "rimborso": true
    }
  ]
}