{
  "slug": "spironolattone",
  "nome": "Spironolattone",
  "atc": "C03DA01",
  "categoria_atc": "Sistema cardiovascolare",
  "n_farmaci": 3,
  "prezzo_min": 3.82,
  "prezzo_medio": 5.82,
  "ha_rimborsato": true,
  "aggiornato": "2026-05-16",
  "farmaci": [
    {
      "nome": "Spironolattone EG 25mg 30cpr",
      "ditta": "EG",
      "prezzo": 3.82,
      "fascia": "A",
      "rimborso": true
    },
    {
      "nome": "Aldactone 100mg 30cpr",
      "ditta": "Pfizer",
      "prezzo": 8.42,
      "fascia": "A",
      "rimborso": true
    },
    {
      "nome": "Spirolang 25mg 30cpr",
      "ditta": "Almirall",
      "prezzo": 5.22,
      "fascia": "A",
      "rimborso": true
    }
  ]
}